jupygcc/__about__.py
jupygcc/__init__.py
jupygcc/gcc_magic.py
jupygcc/utils.py
jupygcc-0.0.6.dist-info/METADATA
jupygcc-0.0.6.dist-info/WHEEL
jupygcc-0.0.6.dist-info/licenses/LICENSE.txt
jupygcc-0.0.6.dist-info/RECORD
