Metadata-Version: 2.3
Name: jupygcc
Version: 0.0.6
Project-URL: Documentation, https://github.com/benabel/jupygcc#readme
Project-URL: Issues, https://github.com/benabel/jupygcc/issues
Project-URL: Source, https://github.com/benabel/jupygcc
Author-email: Benjamin Abel <dev.abel@free.fr>
License-Expression: MIT
License-File: LICENSE.txt
Classifier: Development Status :: 4 - Beta
Classifier: Programming Language :: Python
Classifier: Programming Language :: Python :: 3.8
Classifier: Programming Language :: Python :: 3.9
Classifier: Programming Language :: Python :: 3.10
Classifier: Programming Language :: Python :: 3.11
Classifier: Programming Language :: Python :: 3.12
Classifier: Programming Language :: Python :: Implementation :: CPython
Classifier: Programming Language :: Python :: Implementation :: PyPy
Requires-Python: >=3.8
Requires-Dist: hatch>=1.13.0
